webauthn/__init__.py
webauthn/backends.py
webauthn/conf.py
webauthn/forms.py
webauthn/models.py
webauthn/test_settings.py
webauthn/urls.py
webauthn/views.py
webauthn/migrations/0001_initial.py
webauthn/migrations/__init__.py
webauthn/templatetags/__init__.py
webauthn/templatetags/webauthn.py
webauthn/tests/__init__.py
webauthn/tests/test_sample.py
django_webauthn-0.0.2.dist-info/LICENSE
django_webauthn-0.0.2.dist-info/METADATA
django_webauthn-0.0.2.dist-info/WHEEL
django_webauthn-0.0.2.dist-info/dependency_links.txt
django_webauthn-0.0.2.dist-info/top_level.txt
django_webauthn-0.0.2.dist-info/RECORD
